LICENSE
MANIFEST.in
README
setup.py
manpage/ovm-ctl.1
ovm_ctl/__init__.py
ovm_ctl/attach.py
ovm_ctl/bindings.py
ovm_ctl/boot.py
ovm_ctl/ca.pem
ovm_ctl/console.py
ovm_ctl/context.py
ovm_ctl/create.py
ovm_ctl/destroy.py
ovm_ctl/detach.py
ovm_ctl/extra
ovm_ctl/helping.py
ovm_ctl/man_writing.py
ovm_ctl/ovm-ctl
ovm_ctl/parsedocs.py
ovm_ctl/password.py
ovm_ctl/routes.py
ovm_ctl/setram.py
ovm_ctl/show.py
ovm_ctl/shutdown.py
ovm_ctl/sslverify.py
ovm_ctl/webbindings.py
ovm_ctl/wizard.py
ovm_ctl.egg-info/PKG-INFO
ovm_ctl.egg-info/SOURCES.txt
ovm_ctl.egg-info/dependency_links.txt
ovm_ctl.egg-info/not-zip-safe
ovm_ctl.egg-info/top_level.txt