Metadata-Version: 1.0
Name: ovm-ctl
Version: 0.4.4.3
Summary: Python bindings and command line utility for the OrionVM IaaS platform
Home-page: https://github.com/orionvm/ovm-ctl
Author: Chris McClymont
Author-email: chris.mcclymont@orionvm.com
License: BSD Simplified 2-clause licence
Platform: UNKNOWN
